<!--
Schema fragment for table snmp_mibs

Copyright (C) 2011-2015 Holger Schletz <holger.schletz@web.de>

This program is free software; you can redistribute it and/or modify it
under the terms of the GNU General Public License as published by the Free
Software Foundation; either version 2 of the License, or (at your option)
any later version.

This program is distributed in the hope that it will be useful, but WITHOUT
ANY WARRANTY; without even the implied warranty of MERCHANTABILITY or
FITNESS FOR A PARTICULAR PURPOSE. See the GNU General Public License for
more details.

You should have received a copy of the GNU General Public License along with
this program; if not, write to the Free Software Foundation, Inc.,
51 Franklin Street, Fifth Floor, Boston, MA  02110-1301, USA.
-->

 <table>

  <name>snmp_mibs</name>

  <declaration>

   <field>
    <name>id</name>
    <type>integer</type>
    <notnull>true</notnull>
    <autoincrement>1</autoincrement>
    <length>4</length>
   </field>

   <field>
    <name>vendor</name>
    <type>text</type>
    <length>255</length>
   </field>

   <field>
    <name>url</name>
    <type>text</type>
    <length>255</length>
   </field>

   <field>
    <name>checksum</name>
    <type>text</type>
    <length>255</length>
   </field>

   <field>
    <name>version</name>
    <type>text</type>
    <length>5</length>
   </field>

   <field>
    <name>parser</name>
    <type>text</type>
    <length>5</length>
   </field>

   <index>
    <name>snmp_mibs_primary</name>
    <primary>true</primary>
    <field>
     <name>id</name>
    </field>
   </index>

  </declaration>

 </table>
